{
  "name": "Technician Utilization Report",
  "report_name": "Technician Utilization Report",
  "doctype": "Report",
  "ref_doctype": "Timesheet",
  "is_standard": "Yes",
  "report_type": "Script Report",
  "module": "Car Repair Management",
  "filters": [
    {"fieldname": "from_date", "label": "From Date", "fieldtype": "Date", "reqd": 1},
    {"fieldname": "to_date", "label": "To Date", "fieldtype": "Date", "reqd": 1},
    {"fieldname": "employee", "label": "Employee", "fieldtype": "Link", "options": "Employee"}
  ]
}
